gym_crypto/__init__.py
gym_crypto/configs.py
gym_crypto/data/BTC.csv
gym_crypto/data/EOS.csv
gym_crypto/data/ETH.csv
gym_crypto/data/LTC.csv
gym_crypto/data/XRP.csv
gym_crypto/data/__init__.py
gym_crypto/data_utils/__init__.py
gym_crypto/data_utils/data_utils.py
gym_crypto/envs/__init__.py
gym_crypto/envs/crypto_env.py
gym_crypto/tests/__init__.py
gym_crypto/tests/test_crypto_env.py
gym_crypto/tests/test_data_utils.py
gym_crypto/wrappers/__init__.py
gym_crypto-0.0.4.dist-info/LICENSE.txt
gym_crypto-0.0.4.dist-info/METADATA
gym_crypto-0.0.4.dist-info/WHEEL
gym_crypto-0.0.4.dist-info/top_level.txt
gym_crypto-0.0.4.dist-info/RECORD
