Metadata-Version: 2.1
Name: gym-crypto
Version: 0.0.4
Summary: Reinforcement Learning OpenAI Gym environment for crypto-currency trading.
Home-page: https://github.com/dema-u/gym-crypto
Author: Dema Ushchapovskyy, Suraj Tirupati
Author-email: du116@ic.ac.uk
License: MIT
Keywords: RL,OpenAI,Gym
Platform: UNKNOWN
Requires-Dist: gym
Requires-Dist: pandas
Requires-Dist: numpy
